{"proxies":{"ti.googlesignin.GooglesigninModule":{"superPackageName":"org.appcelerator.kroll","methods":{"signIn":{"runOnUiThread":false,"hasInvocation":false,"args":[],"apiName":"signIn","converter":"org.appcelerator.kroll.KrollConverter","defaultValueProvider":"org.appcelerator.kroll.KrollConverter","name":"__default_name__","returnType":"void"},"initialize":{"runOnUiThread":false,"hasInvocation":false,"args":[{"converter":"org.appcelerator.kroll.KrollConverter","defaultValueProvider":"org.appcelerator.kroll.KrollConverter","name":"opts","sourceName":"opts","type":"org.appcelerator.kroll.KrollDict"}],"apiName":"initialize","converter":"org.appcelerator.kroll.KrollConverter","defaultValueProvider":"org.appcelerator.kroll.KrollConverter","name":"__default_name__","returnType":"void"}},"superProxyBindingClassName":"org.appcelerator.kroll.KrollModuleBindingGen","proxyClassName":"GooglesigninModule","proxyAttrs":{"propertyAccessors":[],"fullAPIName":"Googlesignin","name":"Googlesignin","proxyClassName":"ti.googlesignin.GooglesigninModule","isTopLevel":false,"id":"ti.googlesignin"},"packageName":"ti.googlesignin","sourceName":"ti.googlesignin.GooglesigninModuleBindingGen","superProxyClassName":"KrollModule","isModule":true,"genClassName":"GooglesigninModuleBindingGen","onAppCreate":"onAppCreate"}},"modules":{"ti.googlesignin.GooglesigninModule":{"apiName":"Googlesignin"}}}